{
  "Донецкая область": {
    "type": "drone",
    "text": "Советский район ДНР.  населённый пункт Северный, Ханженково\nТревога по БПЛА, возможно ФПВ",
    "channel": "LPRalarm",
    "updated_at": "2026-07-14T21:27:23+00:00",
    "expires_at": "2026-07-14T22:27:23+00:00"
  },
  "Запорожская область": {
    "type": "drone",
    "text": "Приморск и близлежащие\nЗапорожская область РФ\nТревога по БПЛА\nВозможно с выходом в Азовское море",
    "channel": "kupolrussia",
    "updated_at": "2026-07-14T21:12:03+00:00",
    "expires_at": "2026-07-14T22:12:03+00:00"
  },
  "Краснодарский край": {
    "type": "drone",
    "text": "Крымск и близлежащие\nТревога по БПЛА\nКраснодарский край",
    "channel": "kupolrussia",
    "updated_at": "2026-07-14T21:36:24+00:00",
    "expires_at": "2026-07-14T22:36:24+00:00"
  },
  "Республика Крым": {
    "type": "drone",
    "text": "Джанкойский район\nТревога по БПЛА\nРеспублика Крым",
    "channel": "kupolrussia",
    "updated_at": "2026-07-14T21:35:23+00:00",
    "expires_at": "2026-07-14T22:35:23+00:00"
  }
}