{
  "tracks": [
    {
      "id": "drone_1784338734.0_Котельники",
      "type": "drone",
      "points": [
        {
          "lat": 55.661668,
          "lon": 37.8673073,
          "time": "2026-07-18T01:38:54+00:00",
          "location_name": "Котельники",
          "region": "Московская область"
        },
        {
          "lat": 55.7813357,
          "lon": 38.6507838,
          "time": "2026-07-18T02:07:43+00:00",
          "location_name": "Павловский Посад",
          "region": "Московская область"
        },
        {
          "lat": 55.7813357,
          "lon": 38.6507838,
          "time": "2026-07-18T02:15:56+00:00",
          "location_name": "Павловский Посад",
          "region": "Московская область"
        },
        {
          "lat": 55.578403,
          "lon": 39.5437584,
          "time": "2026-07-18T02:49:09+00:00",
          "location_name": "Шатура",
          "region": "Московская область"
        },
        {
          "lat": 55.578403,
          "lon": 39.5437584,
          "time": "2026-07-18T03:09:45+00:00",
          "location_name": "Шатура",
          "region": "Московская область"
        }
      ],
      "last_time": "2026-07-18T03:09:45+00:00"
    },
    {
      "id": "drone_1784340956.0_Котельники",
      "type": "drone",
      "points": [
        {
          "lat": 55.661668,
          "lon": 37.8673073,
          "time": "2026-07-18T02:15:56+00:00",
          "location_name": "Котельники",
          "region": "Московская область"
        },
        {
          "lat": 55.6783142,
          "lon": 37.89377,
          "time": "2026-07-18T02:49:09+00:00",
          "location_name": "Люберцы",
          "region": "Московская область"
        },
        {
          "lat": 55.5709361,
          "lon": 38.2282099,
          "time": "2026-07-18T03:04:46+00:00",
          "location_name": "Раменское",
          "region": "Московская область"
        },
        {
          "lat": 55.5709361,
          "lon": 38.2282099,
          "time": "2026-07-18T03:11:30+00:00",
          "location_name": "Раменское",
          "region": "Московская область"
        },
        {
          "lat": 55.5709361,
          "lon": 38.2282099,
          "time": "2026-07-18T03:16:52+00:00",
          "location_name": "Раменское",
          "region": "Московская область"
        }
      ],
      "last_time": "2026-07-18T03:16:52+00:00"
    },
    {
      "id": "drone_1784344097.0_Дмитровский",
      "type": "drone",
      "points": [
        {
          "lat": 52.6670934,
          "lon": 35.5664814,
          "time": "2026-07-18T03:08:17+00:00",
          "location_name": "Дмитровский",
          "region": "Орловская область"
        },
        {
          "lat": 52.6670934,
          "lon": 35.5664814,
          "time": "2026-07-18T03:36:09+00:00",
          "location_name": "Дмитровский",
          "region": "Орловская область"
        }
      ],
      "last_time": "2026-07-18T03:36:09+00:00"
    },
    {
      "id": "drone_1784344111.0_Сосковский",
      "type": "drone",
      "points": [
        {
          "lat": 52.742656,
          "lon": 35.3808815,
          "time": "2026-07-18T03:08:31+00:00",
          "location_name": "Сосковский",
          "region": "Орловская область"
        }
      ],
      "last_time": "2026-07-18T03:08:31+00:00"
    },
    {
      "id": "drone_1784344134.0_Лебедянский",
      "type": "drone",
      "points": [
        {
          "lat": 52.9521848,
          "lon": 39.2048344,
          "time": "2026-07-18T03:08:54+00:00",
          "location_name": "Лебедянский",
          "region": "Липецкая область"
        }
      ],
      "last_time": "2026-07-18T03:08:54+00:00"
    },
    {
      "id": "drone_1784344157.0_Пронский",
      "type": "drone",
      "points": [
        {
          "lat": 54.1832933,
          "lon": 39.5528984,
          "time": "2026-07-18T03:09:17+00:00",
          "location_name": "Пронский",
          "region": "Рязанская область"
        }
      ],
      "last_time": "2026-07-18T03:09:17+00:00"
    },
    {
      "id": "missile_1784344765.0_Хомутовский",
      "type": "missile",
      "points": [
        {
          "lat": 46.9285426,
          "lon": 142.8645265,
          "time": "2026-07-18T03:19:25+00:00",
          "location_name": "Хомутовский",
          "region": null
        },
        {
          "lat": 46.9285426,
          "lon": 142.8645265,
          "time": "2026-07-18T03:19:29+00:00",
          "location_name": "Хомутовский",
          "region": null
        }
      ],
      "last_time": "2026-07-18T03:19:29+00:00"
    },
    {
      "id": "drone_1784344811.0_Симферопольский",
      "type": "drone",
      "points": [
        {
          "lat": 55.5762336,
          "lon": 110.354989,
          "time": "2026-07-18T03:20:11+00:00",
          "location_name": "Симферопольский",
          "region": null
        },
        {
          "lat": 55.5762336,
          "lon": 110.354989,
          "time": "2026-07-18T03:20:15+00:00",
          "location_name": "Симферопольский",
          "region": null
        },
        {
          "lat": 55.5762336,
          "lon": 110.354989,
          "time": "2026-07-18T03:27:39+00:00",
          "location_name": "Симферопольский",
          "region": null
        }
      ],
      "last_time": "2026-07-18T03:27:39+00:00"
    },
    {
      "id": "drone_1784344872.0_Орел",
      "type": "drone",
      "points": [
        {
          "lat": 52.9709262,
          "lon": 36.0642127,
          "time": "2026-07-18T03:21:12+00:00",
          "location_name": "Орел",
          "region": "Орловская область"
        },
        {
          "lat": 52.9856621,
          "lon": 35.9383453,
          "time": "2026-07-18T03:37:31+00:00",
          "location_name": "Орловский",
          "region": "Орловская область"
        }
      ],
      "last_time": "2026-07-18T03:37:31+00:00"
    },
    {
      "id": "drone_1784344909.0_Урицкий",
      "type": "drone",
      "points": [
        {
          "lat": 52.3825189,
          "lon": 37.881624,
          "time": "2026-07-18T03:21:49+00:00",
          "location_name": "Урицкий",
          "region": "Орловская область"
        }
      ],
      "last_time": "2026-07-18T03:21:49+00:00"
    },
    {
      "id": "drone_1784345714.0_Шиловский",
      "type": "drone",
      "points": [
        {
          "lat": 54.4778417,
          "lon": 41.1857928,
          "time": "2026-07-18T03:35:14+00:00",
          "location_name": "Шиловский",
          "region": "Рязанская область"
        }
      ],
      "last_time": "2026-07-18T03:35:14+00:00"
    },
    {
      "id": "drone_1784345734.0_Староюрьевский",
      "type": "drone",
      "points": [
        {
          "lat": 53.366918,
          "lon": 40.7696851,
          "time": "2026-07-18T03:35:34+00:00",
          "location_name": "Староюрьевский",
          "region": "Тамбовская область"
        }
      ],
      "last_time": "2026-07-18T03:35:34+00:00"
    },
    {
      "id": "drone_1784345866.0_Болховский",
      "type": "drone",
      "points": [
        {
          "lat": 53.4361073,
          "lon": 35.9880329,
          "time": "2026-07-18T03:37:46+00:00",
          "location_name": "Болховский",
          "region": "Орловская область"
        }
      ],
      "last_time": "2026-07-18T03:37:46+00:00"
    }
  ]
}