{
  "tracks": [
    {
      "id": "drone_1784799842.0_Белгород",
      "type": "drone",
      "points": [
        {
          "lat": 50.5955595,
          "lon": 36.5873394,
          "time": "2026-07-23T09:44:02+00:00",
          "location_name": "Белгород",
          "region": "Белгородская область"
        },
        {
          "lat": 50.4049335,
          "lon": 36.8796822,
          "time": "2026-07-23T10:10:41+00:00",
          "location_name": "Шебекино",
          "region": "Белгородская область"
        },
        {
          "lat": 50.4597389,
          "lon": 36.7405722,
          "time": "2026-07-23T10:45:05+00:00",
          "location_name": "Маслова Пристань",
          "region": null
        },
        {
          "lat": 50.5955595,
          "lon": 36.5873394,
          "time": "2026-07-23T11:18:44+00:00",
          "location_name": "Белгород",
          "region": null
        },
        {
          "lat": 50.5939358,
          "lon": 36.5762397,
          "time": "2026-07-23T11:24:47+00:00",
          "location_name": "Белгородский",
          "region": "Белгородская область"
        },
        {
          "lat": 50.5955595,
          "lon": 36.5873394,
          "time": "2026-07-23T11:35:39+00:00",
          "location_name": "Белгород",
          "region": null
        }
      ],
      "last_time": "2026-07-23T11:35:39+00:00"
    },
    {
      "id": "drone_1784805414.0_Рыльск",
      "type": "drone",
      "points": [
        {
          "lat": 51.570538,
          "lon": 34.683506,
          "time": "2026-07-23T11:16:54+00:00",
          "location_name": "Рыльск",
          "region": "Курская область"
        },
        {
          "lat": 51.581736,
          "lon": 34.8074557,
          "time": "2026-07-23T11:47:42+00:00",
          "location_name": "Октябрьское",
          "region": null
        }
      ],
      "last_time": "2026-07-23T11:47:51+00:00"
    },
    {
      "id": "drone_1784805887.0_Карнауховка",
      "type": "drone",
      "points": [
        {
          "lat": 50.4612234,
          "lon": 36.7019413,
          "time": "2026-07-23T11:24:47+00:00",
          "location_name": "Карнауховка",
          "region": "Белгородская область"
        },
        {
          "lat": 50.5955595,
          "lon": 36.5873394,
          "time": "2026-07-23T11:35:44+00:00",
          "location_name": "Белгород",
          "region": null
        },
        {
          "lat": 50.4049335,
          "lon": 36.8796822,
          "time": "2026-07-23T12:02:30+00:00",
          "location_name": "Шебекино",
          "region": "Белгородская область"
        }
      ],
      "last_time": "2026-07-23T12:02:30+00:00"
    },
    {
      "id": "drone_1784806425.0_Джанкойский",
      "type": "drone",
      "points": [
        {
          "lat": 55.5394245,
          "lon": 37.5744389,
          "time": "2026-07-23T11:33:45+00:00",
          "location_name": "Джанкойский",
          "region": null
        }
      ],
      "last_time": "2026-07-23T11:33:45+00:00"
    },
    {
      "id": "drone_1784806425.0_Красногвардейский",
      "type": "drone",
      "points": [
        {
          "lat": 56.5014628,
          "lon": 40.5420051,
          "time": "2026-07-23T11:33:45+00:00",
          "location_name": "Красногвардейский",
          "region": null
        }
      ],
      "last_time": "2026-07-23T11:56:21+00:00"
    },
    {
      "id": "drone_1784806425.0_Первомайский",
      "type": "drone",
      "points": [
        {
          "lat": 56.614571,
          "lon": 43.358227,
          "time": "2026-07-23T11:33:45+00:00",
          "location_name": "Первомайский",
          "region": null
        }
      ],
      "last_time": "2026-07-23T11:33:45+00:00"
    },
    {
      "id": "drone_1784806425.0_Высоко",
      "type": "drone",
      "points": [
        {
          "lat": 58.6363282,
          "lon": 34.2987356,
          "time": "2026-07-23T11:33:45+00:00",
          "location_name": "Высоко",
          "region": null
        }
      ],
      "last_time": "2026-07-23T11:33:45+00:00"
    },
    {
      "id": "drone_1784806743.0_Пластуновская",
      "type": "drone",
      "points": [
        {
          "lat": 45.2962422,
          "lon": 39.2662799,
          "time": "2026-07-23T11:39:03+00:00",
          "location_name": "Пластуновская",
          "region": null
        }
      ],
      "last_time": "2026-07-23T11:39:03+00:00"
    },
    {
      "id": "drone_1784806743.0_Динская",
      "type": "drone",
      "points": [
        {
          "lat": 45.2168713,
          "lon": 39.2249757,
          "time": "2026-07-23T11:39:03+00:00",
          "location_name": "Динская",
          "region": null
        },
        {
          "lat": 45.0351532,
          "lon": 38.9772396,
          "time": "2026-07-23T12:01:58+00:00",
          "location_name": "Краснодар",
          "region": null
        }
      ],
      "last_time": "2026-07-23T12:04:23+00:00"
    },
    {
      "id": "drone_1784807262.0_Гвардейское",
      "type": "drone",
      "points": [
        {
          "lat": 43.67239,
          "lon": 44.96241,
          "time": "2026-07-23T11:47:42+00:00",
          "location_name": "Гвардейское",
          "region": null
        }
      ],
      "last_time": "2026-07-23T11:47:51+00:00"
    },
    {
      "id": "drone_1784807692.0_Динской",
      "type": "drone",
      "points": [
        {
          "lat": 45.3846223,
          "lon": 36.7762283,
          "time": "2026-07-23T11:54:52+00:00",
          "location_name": "Динской",
          "region": "Краснодарский край"
        }
      ],
      "last_time": "2026-07-23T11:58:48+00:00"
    },
    {
      "id": "drone_1784807758.0_Комаровка",
      "type": "drone",
      "points": [
        {
          "lat": 56.1819073,
          "lon": 37.2785696,
          "time": "2026-07-23T11:55:58+00:00",
          "location_name": "Комаровка",
          "region": null
        }
      ],
      "last_time": "2026-07-23T11:56:21+00:00"
    },
    {
      "id": "drone_1784807758.0_Полтавка",
      "type": "drone",
      "points": [
        {
          "lat": 54.3642388,
          "lon": 71.7609168,
          "time": "2026-07-23T11:55:58+00:00",
          "location_name": "Полтавка",
          "region": null
        }
      ],
      "last_time": "2026-07-23T11:56:21+00:00"
    },
    {
      "id": "drone_1784808255.0_Лабинск",
      "type": "drone",
      "points": [
        {
          "lat": 44.6347953,
          "lon": 40.7242185,
          "time": "2026-07-23T12:04:15+00:00",
          "location_name": "Лабинск",
          "region": null
        }
      ],
      "last_time": "2026-07-23T12:04:23+00:00"
    },
    {
      "id": "drone_1784808410.0_Симферополь",
      "type": "drone",
      "points": [
        {
          "lat": 51.4645957,
          "lon": 81.5338754,
          "time": "2026-07-23T12:06:50+00:00",
          "location_name": "Симферополь",
          "region": null
        }
      ],
      "last_time": "2026-07-23T12:07:08+00:00"
    },
    {
      "id": "drone_1784809718.0_Спасский",
      "type": "drone",
      "points": [
        {
          "lat": 54.5079588,
          "lon": 40.5809989,
          "time": "2026-07-23T12:28:38+00:00",
          "location_name": "Спасский",
          "region": "Рязанская область"
        }
      ],
      "last_time": "2026-07-23T12:29:50+00:00"
    }
  ]
}