{
  "Донецкая область": {
    "type": "drone",
    "text": "Пантелеймоновка, Енакиево ДНР и близлежащие\nС 55 ВНИМАНИЕ!!!\n$ «> ОБЪЯВЛЕН\n\n\"ЖЕЛТЫЙ УРОВЕНЬ\"\nХх $ ОПАСНОСТИ\nПО БПЛА",
    "channel": "kupolrussia",
    "updated_at": "2026-07-17T14:10:47+00:00",
    "expires_at": "2026-07-17T15:10:47+00:00"
  },
  "Рязанская область": {
    "type": "drone",
    "text": "Рязанская область\nОпасность по БПЛА\n\n❗️Радар по всей России - @radarrussiia\n🌐 Обход белых списков - @Internet_Boost_bot",
    "channel": "radarrussiia",
    "updated_at": "2026-07-17T13:33:27+00:00",
    "expires_at": "2026-07-17T14:33:27+00:00"
  },
  "Брянская область": {
    "type": "drone",
    "text": "Почеп и близлежащие \nОпасность по БПЛА \nБрянская область",
    "channel": "LPRalarm",
    "updated_at": "2026-07-17T13:37:40+00:00",
    "expires_at": "2026-07-17T14:37:40+00:00"
  },
  "Белгородская область": {
    "type": "drone",
    "text": "Дальняя Игуменка\nБелгородская область\nС 55 ВНИМАНИЕ!!!\n$ «> ОБЪЯВЛЕН\n\n\"ЖЕЛТЫЙ УРОВЕНЬ\"\nХх $ ОПАСНОСТИ\nПО БПЛА",
    "channel": "kupolrussia",
    "updated_at": "2026-07-17T14:18:05+00:00",
    "expires_at": "2026-07-17T15:18:05+00:00"
  },
  "Курской область": {
    "type": "drone",
    "text": "Губкинский ГО на стыке с Курской областью фиксации БПЛА",
    "channel": "LPRalarm",
    "updated_at": "2026-07-17T14:08:40+00:00",
    "expires_at": "2026-07-17T15:08:40+00:00"
  },
  "Воронежскую область": {
    "type": "drone",
    "text": "Губкинский МО и далее на Воронежскую область тревога по БПЛА",
    "channel": "kupolrussia",
    "updated_at": "2026-07-17T14:09:24+00:00",
    "expires_at": "2026-07-17T15:09:24+00:00"
  },
  "Липецкую область": {
    "type": "drone",
    "text": "Стык Курской и севера Белгородская область тревога по БПЛА и далее на Липецкую область",
    "channel": "kupolrussia",
    "updated_at": "2026-07-17T14:14:44+00:00",
    "expires_at": "2026-07-17T15:14:44+00:00"
  },
  "Курская область": {
    "type": "drone",
    "text": "Советский район Курская область фиксация БПЛА в направлении Липецкая области",
    "channel": "kupolrussia",
    "updated_at": "2026-07-17T14:23:35+00:00",
    "expires_at": "2026-07-17T15:23:35+00:00"
  },
  "Херсонская область": {
    "type": "drone",
    "text": "Херсонская область РФ \nОпасность по БПЛА Хорнет",
    "channel": "kupolrussia",
    "updated_at": "2026-07-17T14:31:01+00:00",
    "expires_at": "2026-07-17T15:31:01+00:00"
  }
}