{
  "запорожск": {
    "display_name": "Запорожская область",
    "type": "drone",
    "text": "Весёлое Запорожская область РФ\nи далее, возможно, в направлении Мелитополь\nВНИМАНИЕ!!!\n< (> ОБЪЯВЛЕН\n_ ДА \"КРАСНЫЙ УРОВЕНЬ\"\n($) $) ОПАСНОСТИ\nПО БПЛА",
    "channel": "kupolrussia",
    "updated_at": "2026-07-20T19:47:11+00:00",
    "expires_at": "2026-07-20T20:47:11+00:00",
    "count": null,
    "count_approx": false
  },
  "орловск": {
    "display_name": "Орловскую область",
    "type": "drone",
    "text": "Хомутовский район, Курская область - пролёты БПЛА от госграницы в направлении Дмитриевский район, Железногорский район, далее на Орловскую область. \n\n📡Локатор России - @locatorru",
    "channel": "locatorru",
    "updated_at": "2026-07-20T20:33:20+00:00",
    "expires_at": "2026-07-20T21:33:20+00:00",
    "count": null,
    "count_approx": false
  },
  "луганск": {
    "display_name": "Луганская область",
    "type": "drone",
    "text": "Северодонецк и близлежащие и далее в тыл\nТревога по БПЛА\nЛНР",
    "channel": "kupolrussia",
    "updated_at": "2026-07-20T20:35:10+00:00",
    "expires_at": "2026-07-20T21:35:10+00:00",
    "count": null,
    "count_approx": false
  },
  "белгородск": {
    "display_name": "Белгородской области",
    "type": "drone",
    "text": "БПЛА в сторону Алексеевка, Белгородской области от Насоново. \n\nОстрогожск, Лиски внимание. \n\n📡Локатор России - @locatorru",
    "channel": "locatorru",
    "updated_at": "2026-07-20T20:13:16+00:00",
    "expires_at": "2026-07-20T21:13:16+00:00",
    "count": null,
    "count_approx": false
  },
  "донецк": {
    "display_name": "Донецкая область",
    "type": "drone",
    "text": "Трасса Урзуф-Мангуш\nДНР\nВНИМАНИЕ!!!\n< (> ОБЪЯВЛЕН\n_ ДА \"КРАСНЫЙ УРОВЕНЬ\"\n($) $) ОПАСНОСТИ\nПО БПЛА",
    "channel": "kupolrussia",
    "updated_at": "2026-07-20T19:52:50+00:00",
    "expires_at": "2026-07-20T20:52:50+00:00",
    "count": null,
    "count_approx": false
  },
  "херсонск": {
    "display_name": "Херсонская область",
    "type": "drone",
    "text": "Каланчак, Харлы и близлежащие\nХерсонская область РФ\nОпасность по БПЛА",
    "channel": "LPRalarm",
    "updated_at": "2026-07-20T20:31:32+00:00",
    "expires_at": "2026-07-20T21:31:32+00:00",
    "count": null,
    "count_approx": false
  },
  "ростовск": {
    "display_name": "Ростовская область",
    "type": "drone",
    "text": "Ростовская область - внимание по БПЛА от ЛНР. \n\n📡Локатор России - @locatorru",
    "channel": "locatorru",
    "updated_at": "2026-07-20T20:19:19+00:00",
    "expires_at": "2026-07-20T21:19:19+00:00",
    "count": null,
    "count_approx": false
  },
  "воронежск": {
    "display_name": "Воронежская область",
    "type": "drone",
    "text": "Воронежская область, Тамбовская область - опасность по БПЛА. \n\n📡Локатор России - @locatorru",
    "channel": "locatorru",
    "updated_at": "2026-07-20T20:29:20+00:00",
    "expires_at": "2026-07-20T21:29:20+00:00",
    "count": null,
    "count_approx": false
  },
  "тамбовск": {
    "display_name": "Тамбовская область",
    "type": "drone",
    "text": "Тамбовская область \nОпасность по БПЛА",
    "channel": "vrv_radar",
    "updated_at": "2026-07-20T20:30:15+00:00",
    "expires_at": "2026-07-20T21:30:15+00:00",
    "count": null,
    "count_approx": false
  },
  "курск": {
    "display_name": "Курская область",
    "type": "drone",
    "text": "Хомутовский район, Курская область - пролёты БПЛА от госграницы в направлении Дмитриевский район, Железногорский район, далее на Орловскую область. \n\n📡Локатор России - @locatorru",
    "channel": "locatorru",
    "updated_at": "2026-07-20T20:33:20+00:00",
    "expires_at": "2026-07-20T21:33:20+00:00",
    "count": null,
    "count_approx": false
  },
  "краснодарск": {
    "display_name": "Краснодарский край",
    "type": "drone",
    "text": "Ейский район\nКраснодарский край\nОпасность по БПЛА\n\n❗️Радар по всей России - @radarrussiia\n🌐 Обход белых списков - @Internet_Boost_bot",
    "channel": "radarrussiia",
    "updated_at": "2026-07-20T20:45:15+00:00",
    "expires_at": "2026-07-20T21:45:15+00:00",
    "count": null,
    "count_approx": false
  },
  "крым": {
    "display_name": "Республика Крым",
    "type": "drone",
    "text": "Почтовое\nСкалистое\nБахчисарай и близлежащие \nОпасность по БПЛА \nРеспублика Крым",
    "channel": "LPRalarm",
    "updated_at": "2026-07-20T20:45:24+00:00",
    "expires_at": "2026-07-20T21:45:24+00:00",
    "count": null,
    "count_approx": false
  }
}